traffic_light_controller.v
`timescale 1ns / 1ps
module Traffic_Light_Controller(


    input clk,rst,
    output reg [2:0]light_M1,
    output reg [2:0]light_S,
    output reg [2:0]light_MT,
    output reg [2:0]light_M2
    );
    
    parameter  S1=0, S2=1, S3 =2, S4=3, S5=4,S6=5;
    reg [3:0]count;
    reg[2:0] ps;
    parameter  sec7=7,sec5=5,sec2=2,sec3=3;

   
    
    always@(posedge clk or posedge rst)
        begin
        if(rst==1)
        begin
        ps<=S1;
        count<=0;
        end
        else
        
      
       
            
            case(ps)
                S1: if(count<sec7)
                        begin
                        ps<=S1;
                        count<=count+1;
                        end
                    else
                        begin
                        ps<=S2;
                        count<=0;
                        end
                S2: if(count<sec2)
                        begin
                        ps<=S2;
                        count<=count+1;
                        end

                    else
                        begin
                        ps<=S3;
                        count<=0;
                        end
                S3: if(count<sec5)
                        begin
                        ps<=S3;
                        count<=count+1;
                        end

                    else
                        begin
                        ps<=S4;
                        count<=0;
                        end
                S4:if(count<sec2)
                        begin
                        ps<=S4;
                        count<=count+1;
                        end

                    else
                        begin
                        ps<=S5;
                        count<=0;
                        end
                S5:if(count<sec3)
                        begin
                        ps<=S5;
                        count<=count+1;
                        end

                    else
                        begin
                        ps<=S6;
                        count<=0;
                        end

                S6:if(count<sec2)
                        begin
                        ps<=S6;
                        count<=count+1;
                        end

                    else
                        begin
                        ps<=S1;
                        count<=0;
                        end
                default: ps<=S1;
                endcase
            end   

            always@(ps)    
            begin
                
                case(ps)
                     
                    S1:
                    begin
                       light_M1<=3'b001;
                       light_M2<=3'b001;
                       light_MT<=3'b100;
                       light_S<=3'b100;
                    end
                    S2:
                    begin 
                       light_M1<=3'b001;
                       light_M2<=3'b010;
                       light_MT<=3'b100;
                       light_S<=3'b100;
                    end
                    S3:
                    begin
                       light_M1<=3'b001;
                       light_M2<=3'b100;
                       light_MT<=3'b001;
                       light_S<=3'b100;
                    end
                    S4:
                    begin
                       light_M1<=3'b010;
                       light_M2<=3'b100;
                       light_MT<=3'b010;
                       light_S<=3'b100;
                    end
                    S5:
                    begin
                       light_M1<=3'b100;
                       light_M2<=3'b100;
                       light_MT<=3'b100;
                       light_S<=3'b001;
                    end
                    S6:
                    begin 
                       light_M1<=3'b100;
                       light_M2<=3'b100;
                       light_MT<=3'b100;
                       light_S<=3'b010;
                    end
                    default:
                    begin 
                       light_M1<=3'b000;
                       light_M2<=3'b000;
                       light_MT<=3'b000;
                       light_S<=3'b000;
                    end
                    endcase
            end                
              

endmodule

traffic_light_controller_tb.v
module Traffic_Light_Controller_TB;

    reg clk, rst;
    wire [2:0] light_M1;
    wire [2:0] light_S;
    wire [2:0] light_MT;
    wire [2:0] light_M2;

    // Instantiate the Traffic_Light_Controller module
    Traffic_Light_Controller dut (
        .clk(clk),
        .rst(rst),
        .light_M1(light_M1),
        .light_S(light_S),
        .light_MT(light_MT),
        .light_M2(light_M2)
    );

    // Generate the clock signal
    initial begin
        clk = 1'b0;
        forever #(5) clk = ~clk;  // 10 time units clock period
    end

    // Apply the reset and other test stimuli
    initial begin
        rst = 1'b0;
        #10 rst = 1'b1;  // Apply reset
        #20 rst = 1'b0;  // Release reset

        // Run simulation for sufficient time to observe state transitions
        #1000;
        $finish;
    end

    // Monitor the outputs
    initial begin
        $monitor("Time=%0d: clk=%b, rst=%b, light_M1=%b, light_S=%b, light_MT=%b, light_M2=%b",
                 $time, clk, rst, light_M1, light_S, light_MT, light_M2);
    end

    // VCD Dump
    initial begin
        $dumpfile("traffic_light_controller_tb.vcd"); // Specify the VCD file name
        $dumpvars(0, Traffic_Light_Controller_TB);    // Dump all variables
    end

endmodule

traffic_light_controller_tb.vcd
$date
	Sat Aug 31 21:26:48 2024
$end
$version
	Icarus Verilog
$end
$timescale
	1ps
$end
$scope module Traffic_Light_Controller_TB $end
$var wire 3 ! light_S [2:0] $end
$var wire 3 " light_MT [2:0] $end
$var wire 3 # light_M2 [2:0] $end
$var wire 3 $ light_M1 [2:0] $end
$var reg 1 % clk $end
$var reg 1 & rst $end
$scope module dut $end
$var wire 1 % clk $end
$var wire 1 & rst $end
$var parameter 32 ' S1 $end
$var parameter 32 ( S2 $end
$var parameter 32 ) S3 $end
$var parameter 32 * S4 $end
$var parameter 32 + S5 $end
$var parameter 32 , S6 $end
$var parameter 32 - sec2 $end
$var parameter 32 . sec3 $end
$var parameter 32 / sec5 $end
$var parameter 32 0 sec7 $end
$var reg 4 1 count [3:0] $end
$var reg 3 2 light_M1 [2:0] $end
$var reg 3 3 light_M2 [2:0] $end
$var reg 3 4 light_MT [2:0] $end
$var reg 3 5 light_S [2:0] $end
$var reg 3 6 ps [2:0] $end
$upscope $end
$upscope $end
$enddefinitions $end
$comment Show the parameter values. $end
$dumpall
b111 0
b101 /
b11 .
b10 -
b101 ,
b100 +
b11 *
b10 )
b1 (
b0 '
$end
#0
$dumpvars
bx 6
bx 5
bx 4
bx 3
bx 2
bx 1
0&
0%
bx $
bx #
bx "
bx !
$end
#5000
b100 !
b100 5
b100 "
b100 4
b1 #
b1 3
b1 $
b1 2
b0 6
1%
#10000
b0 1
0%
1&
#15000
1%
#20000
0%
#25000
1%
#30000
0%
0&
#35000
b1 1
1%
#40000
0%
#45000
b10 1
1%
#50000
0%
#55000
b11 1
1%
#60000
0%
#65000
b100 1
1%
#70000
0%
#75000
b101 1
1%
#80000
0%
#85000
b110 1
1%
#90000
0%
#95000
b111 1
1%
#100000
0%
#105000
b10 #
b10 3
b0 1
b1 6
1%
#110000
0%
#115000
b1 1
1%
#120000
0%
#125000
b10 1
1%
#130000
0%
#135000
b1 "
b1 4
b100 #
b100 3
b0 1
b10 6
1%
#140000
0%
#145000
b1 1
1%
#150000
0%
#155000
b10 1
1%
#160000
0%
#165000
b11 1
1%
#170000
0%
#175000
b100 1
1%
#180000
0%
#185000
b101 1
1%
#190000
0%
#195000
b10 "
b10 4
b10 $
b10 2
b0 1
b11 6
1%
#200000
0%
#205000
b1 1
1%
#210000
0%
#215000
b10 1
1%
#220000
0%
#225000
b1 !
b1 5
b100 "
b100 4
b100 $
b100 2
b0 1
b100 6
1%
#230000
0%
#235000
b1 1
1%
#240000
0%
#245000
b10 1
1%
#250000
0%
#255000
b11 1
1%
#260000
0%
#265000
b10 !
b10 5
b0 1
b101 6
1%
#270000
0%
#275000
b1 1
1%
#280000
0%
#285000
b10 1
1%
#290000
0%
#295000
b100 !
b100 5
b1 #
b1 3
b1 $
b1 2
b0 1
b0 6
1%
#300000
0%
#305000
b1 1
1%
#310000
0%
#315000
b10 1
1%
#320000
0%
#325000
b11 1
1%
#330000
0%
#335000
b100 1
1%
#340000
0%
#345000
b101 1
1%
#350000
0%
#355000
b110 1
1%
#360000
0%
#365000
b111 1
1%
#370000
0%
#375000
b10 #
b10 3
b0 1
b1 6
1%
#380000
0%
#385000
b1 1
1%
#390000
0%
#395000
b10 1
1%
#400000
0%
#405000
b1 "
b1 4
b100 #
b100 3
b0 1
b10 6
1%
#410000
0%
#415000
b1 1
1%
#420000
0%
#425000
b10 1
1%
#430000
0%
#435000
b11 1
1%
#440000
0%
#445000
b100 1
1%
#450000
0%
#455000
b101 1
1%
#460000
0%
#465000
b10 "
b10 4
b10 $
b10 2
b0 1
b11 6
1%
#470000
0%
#475000
b1 1
1%
#480000
0%
#485000
b10 1
1%
#490000
0%
#495000
b1 !
b1 5
b100 "
b100 4
b100 $
b100 2
b0 1
b100 6
1%
#500000
0%
#505000
b1 1
1%
#510000
0%
#515000
b10 1
1%
#520000
0%
#525000
b11 1
1%
#530000
0%
#535000
b10 !
b10 5
b0 1
b101 6
1%
#540000
0%
#545000
b1 1
1%
#550000
0%
#555000
b10 1
1%
#560000
0%
#565000
b100 !
b100 5
b1 #
b1 3
b1 $
b1 2
b0 1
b0 6
1%
#570000
0%
#575000
b1 1
1%
#580000
0%
#585000
b10 1
1%
#590000
0%
#595000
b11 1
1%
#600000
0%
#605000
b100 1
1%
#610000
0%
#615000
b101 1
1%
#620000
0%
#625000
b110 1
1%
#630000
0%
#635000
b111 1
1%
#640000
0%
#645000
b10 #
b10 3
b0 1
b1 6
1%
#650000
0%
#655000
b1 1
1%
#660000
0%
#665000
b10 1
1%
#670000
0%
#675000
b1 "
b1 4
b100 #
b100 3
b0 1
b10 6
1%
#680000
0%
#685000
b1 1
1%
#690000
0%
#695000
b10 1
1%
#700000
0%
#705000
b11 1
1%
#710000
0%
#715000
b100 1
1%
#720000
0%
#725000
b101 1
1%
#730000
0%
#735000
b10 "
b10 4
b10 $
b10 2
b0 1
b11 6
1%
#740000
0%
#745000
b1 1
1%
#750000
0%
#755000
b10 1
1%
#760000
0%
#765000
b1 !
b1 5
b100 "
b100 4
b100 $
b100 2
b0 1
b100 6
1%
#770000
0%
#775000
b1 1
1%
#780000
0%
#785000
b10 1
1%
#790000
0%
#795000
b11 1
1%
#800000
0%
#805000
b10 !
b10 5
b0 1
b101 6
1%
#810000
0%
#815000
b1 1
1%
#820000
0%
#825000
b10 1
1%
#830000
0%
#835000
b100 !
b100 5
b1 #
b1 3
b1 $
b1 2
b0 1
b0 6
1%
#840000
0%
#845000
b1 1
1%
#850000
0%
#855000
b10 1
1%
#860000
0%
#865000
b11 1
1%
#870000
0%
#875000
b100 1
1%
#880000
0%
#885000
b101 1
1%
#890000
0%
#895000
b110 1
1%
#900000
0%
#905000
b111 1
1%
#910000
0%
#915000
b10 #
b10 3
b0 1
b1 6
1%
#920000
0%
#925000
b1 1
1%
#930000
0%
#935000
b10 1
1%
#940000
0%
#945000
b1 "
b1 4
b100 #
b100 3
b0 1
b10 6
1%
#950000
0%
#955000
b1 1
1%
#960000
0%
#965000
b10 1
1%
#970000
0%
#975000
b11 1
1%
#980000
0%
#985000
b100 1
1%
#990000
0%
#995000
b101 1
1%
#1000000
0%
#1005000
b10 "
b10 4
b10 $
b10 2
b0 1
b11 6
1%
#1010000
0%
#1015000
b1 1
1%
#1020000
0%
#1025000
b10 1
1%
